LICENSE
README.md
setup.py
pyOwen/__init__.py
pyOwen/__main__.py
pyOwen/configs.py
pyOwen/version.py
pyOwen/dB/__init__.py
pyOwen/dB/_core.py
pyOwen/dB/afk_db.py
pyOwen/dB/antiflood_db.py
pyOwen/dB/asst_fns.py
pyOwen/dB/asstcmd_db.py
pyOwen/dB/blacklist_chat_db.py
pyOwen/dB/blacklist_db.py
pyOwen/dB/botchat_db.py
pyOwen/dB/broadcast_db.py
pyOwen/dB/ch_db.py
pyOwen/dB/echo_db.py
pyOwen/dB/filestore_db.py
pyOwen/dB/filter_db.py
pyOwen/dB/forcesub_db.py
pyOwen/dB/gban_mute_db.py
pyOwen/dB/gcast_blacklist_db.py
pyOwen/dB/greetings_db.py
pyOwen/dB/logusers_db.py
pyOwen/dB/mute_db.py
pyOwen/dB/night_db.py
pyOwen/dB/notes_db.py
pyOwen/dB/nsfw_db.py
pyOwen/dB/pmpermit_db.py
pyOwen/dB/snips_db.py
pyOwen/dB/vc_sudos.py
pyOwen/dB/warn_db.py
pyOwen/functions/FastTelethon.py
pyOwen/functions/__init__.py
pyOwen/functions/admins.py
pyOwen/functions/gDrive.py
pyOwen/functions/google_image.py
pyOwen/functions/helper.py
pyOwen/functions/info.py
pyOwen/functions/misc.py
pyOwen/functions/tools.py
pyOwen/functions/ytdl.py
pyOwen/misc/__init__.py
pyOwen/misc/_assistant.py
pyOwen/misc/_decorators.py
pyOwen/misc/_supporter.py
pyOwen/misc/_wrappers.py
pyOwen/startup/BaseClient.py
pyOwen/startup/__init__.py
pyOwen/startup/_database.py
pyOwen/startup/_extra.py
pyOwen/startup/connections.py
pyOwen/startup/funcs.py
pyOwen/startup/loader.py
pyOwen/startup/utils.py
py_Owen.egg-info/PKG-INFO
py_Owen.egg-info/SOURCES.txt
py_Owen.egg-info/dependency_links.txt
py_Owen.egg-info/requires.txt
py_Owen.egg-info/top_level.txt