Metadata-Version: 2.1
Name: py-Owen
Version: 1.0
Summary: A Secure and Powerful Python-Telethon Based Library For Owen Userbot.
Home-page: https://github.com/OwenProjects/py-Owen
Author: OwenProjects
Author-email: beratbeywinchester@gmail.com
License: GNU AFFERO GENERAL PUBLIC LICENSE (v3)
Project-URL: Source Code, https://github.com/OwenProjects/py-Owen
Platform: UNKNOWN
Classifier: Programming Language :: Python :: 3
Classifier: Programming Language :: Python :: 3.7
Classifier: Programming Language :: Python :: 3.8
Classifier: Programming Language :: Python :: 3.9
Classifier: License :: OSI Approved :: GNU General Public License v3 (GPLv3)
Classifier: Operating System :: OS Independent
Requires-Python: >3.6, <3.10
License-File: LICENSE
